lazyverdi/__init__.py
lazyverdi/app.py
lazyverdi/commands/__init__.py
lazyverdi/commands/base.py
lazyverdi/commands/formatters.py
lazyverdi/commands/parsers.py
lazyverdi/core/__init__.py
lazyverdi/core/batch_loader.py
lazyverdi/core/config.py
lazyverdi/core/runner.py
lazyverdi/ui/__init__.py
lazyverdi/ui/panels/__init__.py
lazyverdi/ui/panels/command_panel.py
lazyverdi/ui/panels/info_panel.py
lazyverdi/ui/panels/modals.py
lazyverdi/ui/panels/results_panel.py
lazyverdi/ui/panels/table_panel.py
lazyverdi-1.0.1.dist-info/METADATA
lazyverdi-1.0.1.dist-info/WHEEL
lazyverdi-1.0.1.dist-info/entry_points.txt
lazyverdi-1.0.1.dist-info/licenses/LICENSE
lazyverdi-1.0.1.dist-info/RECORD
